proof_api_client/__init__.py
proof_api_client/client.py
proof_api_client/model.py
proof_api_client-0.2.1.dist-info/METADATA
proof_api_client-0.2.1.dist-info/WHEEL
proof_api_client-0.2.1.dist-info/top_level.txt
proof_api_client-0.2.1.dist-info/RECORD
