Metadata-Version: 2.1
Name: proof-api-client
Version: 0.2.1
Summary: API Client for the Proof DashCam
Author: Oren Sadeh
Project-URL: Homepage, https://github.com/osadeh/proof-api-client
Project-URL: Bug Tracker, https://github.com/osadeh/proof-api-client/issues
Classifier: Programming Language :: Python :: 3
Classifier: License :: OSI Approved :: MIT License
Classifier: Operating System :: OS Independent
Requires-Python: >=3.7
